odoo/addons/ambtu/README.md
odoo/addons/ambtu/__init__.py
odoo/addons/ambtu/__manifest__.py
odoo/addons/ambtu/reports/external_layout_standard.xml
odoo/addons/ambtu/reports/report_invoice_document.xml
odoo/addons/ambtu/static/src/img/footer.png
odoo/addons/ambtu/views/ir_qweb_widget_templates.xml
odoo14_addon_ambtu-14.0.1.0.1.dist-info/METADATA
odoo14_addon_ambtu-14.0.1.0.1.dist-info/WHEEL
odoo14_addon_ambtu-14.0.1.0.1.dist-info/top_level.txt
odoo14_addon_ambtu-14.0.1.0.1.dist-info/RECORD
