Metadata-Version: 2.1
Name: odoo14-addon-ambtu
Version: 14.0.1.0.1
Summary: AmbTu module customizations
Home-page: https://git.coopdevs.org/coopdevs/odoo/odoo-addons/odoo-ambtu
Author: Coopdevs Treball SCCL
License: AGPL-3
Platform: UNKNOWN
Classifier: Programming Language :: Python
Classifier: Framework :: Odoo
Classifier: License :: OSI Approved :: GNU Affero General Public License v3
Requires-Python: >=3.6
Requires-Dist: odoo (<14.1dev,>=14.0a)
